smon/__init__.py
smon/oscilloscope.py
smon/sampling.py
smon/smon.png
smon/smon.py
smon/smon_xnode_code.png
smon-1.1.0.dist-info/LICENSE
smon-1.1.0.dist-info/METADATA
smon-1.1.0.dist-info/WHEEL
smon-1.1.0.dist-info/entry_points.txt
smon-1.1.0.dist-info/top_level.txt
smon-1.1.0.dist-info/RECORD
