Metadata-Version: 2.1
Name: smon
Version: 1.1.0
Summary: This is a sensor data oscilloscope for xkit.
Home-page: https://github.com/planxstudio/xkit
Author: chanmin.park
Author-email: devcamp@gmail.com
Keywords: xkit,genlib
Classifier: Programming Language :: Python :: 3
Classifier: License :: OSI Approved :: MIT License
Classifier: Operating System :: OS Independent
Requires-Python: >=3.8
License-File: LICENSE
Requires-Dist: click
Requires-Dist: python-dotenv
Requires-Dist: numpy
Requires-Dist: pyside6
Requires-Dist: pythonqwt
Requires-Dist: genlib
